tsaug/__init__.py
tsaug/_augmenter/__init__.py
tsaug/_augmenter/add_noise.py
tsaug/_augmenter/base.py
tsaug/_augmenter/convolve.py
tsaug/_augmenter/crop.py
tsaug/_augmenter/drift.py
tsaug/_augmenter/dropout.py
tsaug/_augmenter/linear_transform.py
tsaug/_augmenter/pool.py
tsaug/_augmenter/quantize.py
tsaug/_augmenter/resize.py
tsaug/_augmenter/reverse.py
tsaug/_augmenter/time_warp.py
tsaug/visualization/__init__.py
tsaug/visualization/_visualization.py
tsaug-0.2.1.dist-info/LICENSE
tsaug-0.2.1.dist-info/METADATA
tsaug-0.2.1.dist-info/WHEEL
tsaug-0.2.1.dist-info/top_level.txt
tsaug-0.2.1.dist-info/RECORD
