Metadata-Version: 2.1
Name: tsaug
Version: 0.2.1
Summary: A package for time series augmentation
Home-page: https://github.com/arundo/tsaug
Author: Arundo Analytics, Inc.
Maintainer: Tailai Wen
Maintainer-email: tailai.wen@arundo.com
License: Apache License 2.0
Keywords: time series,data augmentation
Platform: UNKNOWN
Classifier: Development Status :: 5 - Production/Stable
Classifier: License :: OSI Approved :: Apache Software License
Classifier: Topic :: Scientific/Engineering
Classifier: Programming Language :: Python :: 3.5
Classifier: Programming Language :: Python :: 3.6
Classifier: Programming Language :: Python :: 3.7
Classifier: Programming Language :: Python :: 3.8
Classifier: Operating System :: POSIX :: Linux
Classifier: Operating System :: Unix
Classifier: Operating System :: MacOS
Classifier: Operating System :: Microsoft :: Windows
Requires-Python: >=3.5
Provides-Extra: dev
Provides-Extra: doc
Provides-Extra: test
